{
    "schemes": [
        "http",
        "https"
    ],
    "swagger": "2.0",
    "info": {
        "description": "Sungora",
        "title": "Sungora API",
        "termsOfService": "http://swagger.io/terms/",
        "contact": {
            "name": "API Support",
            "email": "konstantin@shamiev.ru"
        },
        "license": {
            "name": "Sample License"
        },
        "version": "1.0.0"
    },
    "basePath": "/",
    "paths": {
        "/api/sun/general/file/upload": {
            "post": {
                "consumes": [
                    "multipart/form-data"
                ],
                "produces": [
                    "application/octet-stream"
                ],
                "tags": [
                    "General"
                ],
                "summary": "загрузка файла на сервер",
                "parameters": [
                    {
                        "type": "file",
                        "description": "загружаемый файл",
                        "name": "file",
                        "in": "formData",
                        "required": true
                    }
                ],
                "responses": {
                    "200": {
                        "description": "OK",
                        "schema": {
                            "type": "string"
                        }
                    }
                }
            }
        },
        "/api/sun/general/ping": {
            "get": {
                "tags": [
                    "General"
                ],
                "summary": "ping",
                "responses": {
                    "200": {
                        "description": "OK",
                        "schema": {
                            "type": "string"
                        }
                    }
                }
            }
        },
        "/api/sun/general/version": {
            "get": {
                "tags": [
                    "General"
                ],
                "summary": "получение версии приложения",
                "responses": {
                    "200": {
                        "description": "version",
                        "schema": {
                            "type": "string"
                        }
                    }
                }
            }
        },
        "/api/sun/user-test/{id}": {
            "get": {
                "security": [
                    {
                        "ApiKeyAuth": []
                    }
                ],
                "description": "Тестовый обработчик для примера",
                "consumes": [
                    "application/json"
                ],
                "produces": [
                    "application/json"
                ],
                "tags": [
                    "User"
                ],
                "summary": "Тестовый обработчик для примера",
                "deprecated": true,
                "parameters": [
                    {
                        "type": "string",
                        "description": "ID",
                        "name": "id",
                        "in": "path",
                        "required": true
                    }
                ],
                "responses": {
                    "200": {
                        "description": "пользователь",
                        "schema": {
                            "$ref": "#/definitions/mdsun.User"
                        }
                    },
                    "400": {
                        "description": "отрицательный ответ",
                        "schema": {
                            "type": "string"
                        }
                    }
                }
            }
        },
        "/api/sun/user/{id}": {
            "get": {
                "tags": [
                    "User"
                ],
                "summary": "Получение пользователя",
                "parameters": [
                    {
                        "type": "string",
                        "description": "ID",
                        "name": "id",
                        "in": "path",
                        "required": true
                    }
                ],
                "responses": {
                    "200": {
                        "description": "OK",
                        "schema": {
                            "$ref": "#/definitions/mdsun.User"
                        }
                    }
                }
            },
            "put": {
                "tags": [
                    "User"
                ],
                "summary": "Изменение пользователя",
                "parameters": [
                    {
                        "type": "string",
                        "description": "ID",
                        "name": "id",
                        "in": "path",
                        "required": true
                    },
                    {
                        "description": "пользователь",
                        "name": "data",
                        "in": "body",
                        "required": true,
                        "schema": {
                            "$ref": "#/definitions/mdsun.User"
                        }
                    }
                ],
                "responses": {
                    "200": {
                        "description": "OK",
                        "schema": {
                            "$ref": "#/definitions/mdsun.User"
                        }
                    }
                }
            },
            "post": {
                "tags": [
                    "User"
                ],
                "summary": "Создание пользователя",
                "parameters": [
                    {
                        "description": "пользователь",
                        "name": "data",
                        "in": "body",
                        "required": true,
                        "schema": {
                            "$ref": "#/definitions/mdsun.User"
                        }
                    }
                ],
                "responses": {
                    "200": {
                        "description": "OK",
                        "schema": {
                            "$ref": "#/definitions/mdsun.User"
                        }
                    }
                }
            },
            "delete": {
                "tags": [
                    "User"
                ],
                "summary": "Удаление пользователя",
                "parameters": [
                    {
                        "type": "string",
                        "description": "ID",
                        "name": "id",
                        "in": "path",
                        "required": true
                    }
                ],
                "responses": {
                    "200": {
                        "description": "OK",
                        "schema": {
                            "type": "string"
                        }
                    }
                }
            }
        },
        "/api/sun/users": {
            "get": {
                "tags": [
                    "User"
                ],
                "summary": "Получение списка пользователей",
                "responses": {
                    "200": {
                        "description": "OK",
                        "schema": {
                            "type": "array",
                            "items": {
                                "type": "array",
                                "items": {
                                    "$ref": "#/definitions/mdsun.User"
                                }
                            }
                        }
                    }
                }
            }
        },
        "/api/sun/websocket/gorilla/{id}": {
            "get": {
                "security": [
                    {
                        "ApiKeyAuth": []
                    }
                ],
                "tags": [
                    "Websocket"
                ],
                "summary": "пример работы с веб-сокетом (http://localhost:8080/template/gorilla/index.html)",
                "responses": {
                    "101": {
                        "description": "Switching Protocols to websocket",
                        "schema": {
                            "type": "string"
                        }
                    }
                }
            }
        }
    },
    "definitions": {
        "mdsun.User": {
            "type": "object",
            "properties": {
                "alias": {
                    "type": "array",
                    "items": {
                        "type": "string"
                    }
                },
                "cnt": {
                    "type": "integer"
                },
                "cnt2": {
                    "type": "integer"
                },
                "cnt4": {
                    "type": "integer"
                },
                "cnt8": {
                    "type": "integer"
                },
                "created_at": {
                    "type": "string",
                    "example": "2006-01-02T15:04:05Z"
                },
                "data": {
                    "type": "string",
                    "example": "BYTES"
                },
                "deleted_at": {
                    "type": "string",
                    "example": "2006-01-02T15:04:05Z"
                },
                "description": {
                    "type": "string"
                },
                "duration": {
                    "type": "number",
                    "example": 0
                },
                "id": {
                    "type": "string",
                    "example": "8ca3c9c3-cf1a-47fe-8723-3f957538ce42"
                },
                "is_online": {
                    "type": "boolean"
                },
                "login": {
                    "type": "string"
                },
                "metrika": {
                    "type": "string",
                    "example": "JSON"
                },
                "price": {
                    "type": "number",
                    "example": 0.01
                },
                "summa_one": {
                    "type": "number",
                    "example": 0.01
                },
                "summa_two": {
                    "type": "number",
                    "example": 0.01
                },
                "updated_at": {
                    "type": "string",
                    "example": "2006-01-02T15:04:05Z"
                }
            }
        }
    },
    "securityDefinitions": {
        "ApiKeyAuth": {
            "type": "apiKey",
            "name": "Authorization",
            "in": "header"
        }
    },
    "tags": [
        {
            "description": "Общие запросы",
            "name": "General"
        },
        {
            "description": "Пользователи",
            "name": "User"
        },
        {
            "description": "Чат (веб сокет)",
            "name": "Websocket"
        }
    ]
}